jsm_learn/__init__.py
jsm_learn/jsm_learn.py
jsm_learn/methods.py
jsm_learn-0.2.2.dist-info/licenses/LICENSE
jsm_learn-0.2.2.dist-info/METADATA
jsm_learn-0.2.2.dist-info/WHEEL
jsm_learn-0.2.2.dist-info/top_level.txt
jsm_learn-0.2.2.dist-info/RECORD
