Metadata-Version: 2.4
Name: jsm_learn
Version: 0.2.2
Summary: A Python library for data analysis using JSM-method
Author-email: Mikhail Torkanovskiy <mtorkanovskiy@gmail.com>
License-Expression: MIT
Project-URL: Homepage, https://github.com/reddedpixel/jsm_learn
Project-URL: Issues, https://github.com/reddedpixel/jsm_learn/issues
Classifier: Programming Language :: Python :: 3
Classifier: Operating System :: Microsoft :: Windows :: Windows 11
Requires-Python: >=3.11.9
License-File: LICENSE
Requires-Dist: pandas
Dynamic: license-file
